{
	"$schema": "https://tonytools.win/schemas/dlge.schema.json",
	"hash": "[assembly:/localization/hitman6/conversations/ancestral/hollyhock/41500_pdlc_story/pdlc41511_l3killextrctwve02.sweetdialog?/pdlc41511_l3killextrctwve02_hollyhock_001.sweetdialogitem].pc_dialogevent",
	"DITL": "00B7E83B2B5BFE20",
	"CLNG": "00E3CBB0725ED16C",
	"rootContainer": {
		"type": "WavFile",
		"wavName": "pdlc41511_l3killextrctwve02_hollyhock_001",
		"soundtag": "Voiceover_Handler_ICAEarpiece",
		"defaultWav": "[assembly:/sound/wwise/originals/voices/english(us)/ancestral/hollyhock/41500_pdlc_story/pdlc41511_l3killextrctwve02_hollyhock_001.wav].pc_wes",
		"defaultFfx": "[assembly:/_pro/facefx/exported_animation/english(us)/ancestral/hollyhock/41500_pdlc_story/pdlc41511_l3killextrctwve02_hollyhock_001.animset].pc_animset",
		"languages": {
			"en": "//[HOLLYHOCK]\\\\//(0,7.2)\\\\You did it, 47! You annihilated all the Inhibitors. What satisfaction.//(7.2,37.2)\\\\Now get back to your layer.",
			"fr": "//[HOLLYHOCK]\\\\//(0,7.6)\\\\Vous l'avez fait, 47 ! Vous avez eu tous les répresseurs. Quelle satisfaction...//(7.6,37.6)\\\\Maintenant, rentrez chez vous.",
			"it": "//[HOLLYHOCK]\\\\//(0,30)\\\\Ce l'hai fatta, 47! Hai annientato tutti gli Inibitori. Che soddisfazione. Ora torna al tuo rifugio.",
			"de": "//[HOLLYHOCK]\\\\//(0,7.6)\\\\Sie haben es geschafft, 47. Sie haben alle Inhibitoren ausgelöscht. Wie befriedigend.//(7.6,37.6)\\\\Jetzt zurück in Ihren Unterschlupf.",
			"es": "//[HOLLYHOCK]\\\\//(0,4.850982)\\\\¡Lo has conseguido, 47! Has acabado con todos los inhibidores.//(4.850982,34.85098)\\\\Menuda satisfacción. Y ahora, vuelve a tu plano.",
			"ru": "//[HOLLYHOCK]\\\\//(0,2.4)\\\\Ты справился, 47-й!//(2.4,7.85)\\\\Перебил всех блокаторов! Какое удовольствие.//(7.85,37.85)\\\\Теперь пора возвращаться в свой мир.",
			"cn": "//[HOLLYHOCK]\\\\//(0,7.55)\\\\你做到了，47！你消灭了所有的抑制者。真是令人愉快。//(7.55,37.55)\\\\现在回到你的本体吧。",
			"tc": "//[HOLLYHOCK]\\\\//(0,7.7)\\\\你成功了，47！你消滅了所有抑制者。真是暢快。//(7.7,37.7)\\\\現在回去吧。",
			"jp": "//[HOLLYHOCK]\\\\//(0,7.7)\\\\やったわね、47！インヒビターを全滅させたわ。満足だわ。//(7.7,37.7)\\\\さ、自分の居場所に戻るのよ。"
		}
	}
}
