{
    "$schema": "https://tonytools.win/schemas/dlge.schema.json",
    "hash": "[assembly:/localization/hitman6/conversations/wet/makoyana/43700_story/pdlc43727_l2sniperspotgood.sweetdialog?/pdlc43727_l2sniperspotgood_makoyana_001.sweetdialogitem].pc_dialogevent",
    "DITL": "00B7E83B2B5BFE20",
    "CLNG": "00E3CBB0725ED16C",
    "rootContainer": {
        "type": "WavFile",
        "wavName": "pdlc43727_l2sniperspotgood_makoyana_001",
        "soundtag": "Voiceover_Handler_Dream",
        "defaultWav": "[assembly:/sound/wwise/originals/voices/english(us)/wet/makoyana/43700_story/pdlc43727_l2sniperspotgood_makoyana_001.wav].pc_wes",
        "defaultFfx": "[assembly:/_pro/facefx/exported_animation/english(us)/wet/makoyana/43700_story/pdlc43727_l2sniperspotgood_makoyana_001.animset].pc_animset",
        "languages": {
            "en": "//[MAKOYANA]\\\\//(0,3.05)\\\\Well, they weren't hard to spot, were they?//(3.05,33.05)\\\\So easy, so simple – yet it lacks... creativity.",
            "fr": "//[MAKOYANA]\\\\//(0,30)\\\\Elles n'étaient pas si difficiles à repérer, n'est-ce pas ? Si simple, si évident. Et pourtant, ça manque de... créativité.",
            "it": "//[MAKOYANA]\\\\//(0,30)\\\\Beh, non erano poi così difficili da individuare, non credi? Così semplice eppure così privo di... creatività.",
            "de": "//[MAKOYANA]\\\\//(0,2.781)\\\\Na, die waren nicht schwer zu entdecken, oder?//(2.781,7.382)\\\\So einfach, so leicht – doch es fehlt an ...//(8.311,38.311)\\\\Kreativität.",
            "es": "//[MAKOYANA]\\\\//(0,2.6)\\\\Vaya, no eran tan difíciles de ver, ¿eh?//(2.9,32.9)\\\\Ha sido fácil y sencillo, pero... le falta un poco de creatividad.",
            "ru": "//[MAKOYANA]\\\\//(0,3.19)\\\\Что ж, заметить их было несложно, да?//(3.19,6.145276)\\\\Цели на виду, стреляй сколько хочешь...//(6.145276,36.14528)\\\\Но в этом нет изобретательности.",
            "cn": "//[MAKOYANA]\\\\//(0,30)\\\\好吧，它们不难发现，对吧？太容易太轻松了，但缺乏......创造力。",
            "tc": "//[MAKOYANA]\\\\//(0,30)\\\\嗯，他們並不難找，對吧？多麼簡單，多麼單純—— 但它缺乏......創造力。",
            "jp": "//[MAKOYANA]\\\\//(0,30)\\\\見つけるのは難しくなかったな。単純で、分かりやすい... だが、独創性に欠ける。"
        }
    }
}
